json_lint_tools/__init__.py
json_lint_tools/cli.py
json_lint_tools-0.1.1.dist-info/METADATA
json_lint_tools-0.1.1.dist-info/WHEEL
json_lint_tools-0.1.1.dist-info/entry_points.txt
json_lint_tools-0.1.1.dist-info/RECORD
